language.py
django_default_language-0.0.1.dist-info/LICENSE.txt
django_default_language-0.0.1.dist-info/METADATA
django_default_language-0.0.1.dist-info/WHEEL
django_default_language-0.0.1.dist-info/top_level.txt
django_default_language-0.0.1.dist-info/RECORD
